chatgpt_plugin/__init__.py
chatgpt_plugin/model.py
chatgpt_plugin/plugin.py
chatgpt_plugin/schema.py
chatgpt_plugin/utils.py
chatgpt_plugin-0.0.2.dist-info/LICENSE
chatgpt_plugin-0.0.2.dist-info/METADATA
chatgpt_plugin-0.0.2.dist-info/WHEEL
chatgpt_plugin-0.0.2.dist-info/RECORD
