Metadata-Version: 2.1
Name: chatgpt-plugin
Version: 0.0.2
Summary: 
Author: steven-mi
Author-email: stevenmi@live.de
Requires-Python: >=3.8,<4.0
Classifier: Programming Language :: Python :: 3
Classifier: Programming Language :: Python :: 3.8
Classifier: Programming Language :: Python :: 3.9
Classifier: Programming Language :: Python :: 3.10
Classifier: Programming Language :: Python :: 3.11
Requires-Dist: openai (>=0.27.4,<0.28.0)
Requires-Dist: pydantic (>=1.10.7,<2.0.0)
